{
	"bug_regression_url": "https://www.tapd.cn/20041161/bugtrace/bugreports/stat_other/regression/customreport-1120041161001000076",
	"bug_general_url": "https://www.tapd.cn/20041161/bugtrace/bugreports/stat_general/general",
	"bug_handle_url": "https://www.tapd.cn/20041161/bugtrace/bugreports/stat_age/age/systemreport-1000000000000000015",
	"bug_reg_body": {
		"data[Bugreport][time_type]": 2,
		"data[Bugreport][time_setting][from]": "2005-01-01",
		"data[Bugreport][time_setting][to]": "%s",
		"data[Bugreport][time_setting][count]": 1,
		"data[Bugreport][time_setting][type]": "day",
		"data[Bugreport][xAxis]": "os",
		"version_report_mode_regression": "|",
		"version_report_regression[]": "%s",
		"data[Bugreport][create]": "生成报表",
		"data[Bugreport][title]": "每个平台bug回归分布",
		"data[Bugreport][id]": "",
		"data[Bugreport][issaveas]": "",
		"data[Bugreport][params0]": "regression",
		"data[Bugreport][params1]": "customreport-1120041161001000076",
		"data[Bugreport][charttype]": "Column",
		"data[Bugreport][order_type]": "order_default",
		"data[is_ajax]": "",
		"dsc_token": "T8jsqBftehjenM5Z"
	},
	"bug_gen_body": {
		"data[Bugreport][disxAxis]": "status",
		"data[Bugreport][disyAxis]": "os",
		"data[Bugreport][time_type]": 2,
		"data[Bugreport][time_setting][from]": "2005-01-01",
		"data[Bugreport][time_setting][to]": "%s",
		"data[Bugreport][time_setting][count]": 1,
		"data[Bugreport][time_setting][type]": "day",
		"version_report_mode_distributing": "|",
		"version_report_distributing[]": "%s",
		"data[Bugreport][create]": "生成报表",
		"data[Bugreport][title]": "新建-缺陷分布统计",
		"data[Bugreport][id]": "",
		"data[Bugreport][issaveas]": "",
		"data[Bugreport][params0]": "general",
		"data[Bugreport][params1]": "",
		"data[Bugreport][charttype]": "Column",
		"data[Bugreport][order_type]": "order_default",
		"data[is_ajax]": "",
		"dsc_token": "Sj0AhbR9hzLtA8XZ"
	},
	"bug_requrie_body": {
		"data[Bugreport][disxAxis]": "BugStoryRelation_relative_id",
		"data[Bugreport][disyAxis]": "os",
		"data[Bugreport][time_type]": 2,
		"data[Bugreport][time_setting][from]": "2005-01-01",
		"data[Bugreport][time_setting][to]": "%s",
		"data[Bugreport][time_setting][count]": 1,
		"data[Bugreport][time_setting][type]": "day",
		"version_report_mode_distributing": "|",
		"version_report_distributing[]": "%s",
		"data[Bugreport][create]": "生成报表",
		"data[Bugreport][title]": "新建-缺陷分布统计",
		"data[Bugreport][id]": "",
		"data[Bugreport][issaveas]": "",
		"data[Bugreport][params0]": "general",
		"data[Bugreport][params1]": "",
		"data[Bugreport][charttype]": "Column",
		"data[Bugreport][order_type]": "order_default",
		"data[is_ajax]": "",
		"dsc_token": "vLxT06KevZ92YxZG"
	},
	"bug_handle_body": {
		"data[Bugreport][status][0]": "new",
		"data[Bugreport][status][1]": "in_progress",
		"data[Bugreport][time_type]": 2,
		"data[Bugreport][time_setting][from]": "2005-01-01",
		"data[Bugreport][time_setting][to]": "%s",
		"data[Bugreport][time_setting][count]": 1,
		"data[Bugreport][time_setting][type]": "day",
		"data[Bugreport][create_time_type]": 2,
		"data[Bugreport][create_time_setting][from]": "2005-01-01",
		"data[Bugreport][create_time_setting][to]": "%s",
		"data[Bugreport][create_time_setting][count]": 1,
		"data[Bugreport][create_time_setting][type]": "day",
		"data[Bugreport][AgeIntervalNum]": 2,
		"data[Bugreport][AgeTimeInterval]": "day",
		"version_report_mode_age": "|",
		"version_report_age[]": "%s",
		"data[Bugreport][create]": "生成报表",
		"data[Bugreport][title]": "缺陷年龄统计",
		"data[Bugreport][id]": "",
		"data[Bugreport][issaveas]": "",
		"data[Bugreport][params0]": "age",
		"data[Bugreport][params1]": "systemreport-1000000000000000015",
		"data[Bugreport][charttype]": "Column",
		"data[Bugreport][order_type]": "order_default",
		"data[is_ajax]": "",
		"dsc_token": "6hdGIx9L2E6uqJhp"
	}
}